hashfs/__init__.py
hashfs/__main__.py
hashfs/exceptions.py
hashfs/io.py
hashfs/overlay.py
hashfs/utils.py
pyhashfs-1.0.0.dist-info/LICENSE
pyhashfs-1.0.0.dist-info/METADATA
pyhashfs-1.0.0.dist-info/WHEEL
pyhashfs-1.0.0.dist-info/top_level.txt
pyhashfs-1.0.0.dist-info/RECORD
